<?xml version="1.0" encoding="utf-8"?>
<!--re3data.org Schema for the Description of Research Data Repositories. Version 2.2, December 2014. doi:10.2312/re3.006-->
<r3d:re3data xmlns:r3d="http://www.re3data.org/schema/2-2" xmlns:xsi="http://www.w3.org/2001/XMLSchema-instance" xsi:schemaLocation="http://www.re3data.org/schema/2-2 http://schema.re3data.org/2-2/re3dataV2-2.xsd">
    <r3d:repository>
        <r3d:re3data.orgIdentifier>r3d100010837</r3d:re3data.orgIdentifier>
        <r3d:repositoryName language="eng">Scholarly Database at Indiana University</r3d:repositoryName>
                    <r3d:additionalName language="eng">SDB</r3d:additionalName>
                <r3d:repositoryURL>https://wiki.cns.iu.edu/display/SDBDOC/Scholarly-Database-at-Indiana-University_1246324.html</r3d:repositoryURL>
                <r3d:description language="eng">The Scholarly Database (SDB) at Indiana University aims to serve researchers and practitioners interested in the analysis, modeling, and visualization of large-scale scholarly datasets. The online interface provides access to six datasets: MEDLINE papers, registered Clinical Trials, U.S. Patent and Trademark Office patents (USPTO), National Science Foundation (NSF) funding, National Institutes of Health (NIH) funding, and National Endowment for the Humanities funding – over 26 million records in total.</r3d:description>
                    <r3d:repositoryContact>cns-sdb-dev-l@indiana.edu</r3d:repositoryContact>
                            <r3d:type>disciplinary</r3d:type>
                <r3d:size updated="2019-12-02">six datasets and over 26 million records in total</r3d:size>
        <r3d:startDate></r3d:startDate>
        <r3d:endDate></r3d:endDate>
                    <r3d:repositoryLanguage>eng</r3d:repositoryLanguage>
                            <r3d:subject subjectScheme="DFG">1 Humanities and Social Sciences</r3d:subject>
                    <r3d:subject subjectScheme="DFG">2 Life Sciences</r3d:subject>
                    <r3d:subject subjectScheme="DFG">3 Natural Sciences</r3d:subject>
                    <r3d:subject subjectScheme="DFG">4 Engineering Sciences</r3d:subject>
                <r3d:missionStatementURL>https://cns.iu.edu//docs/handouts/SDB_Flyer_hi.pdf</r3d:missionStatementURL>
                    <r3d:contentType contentTypeScheme="parse">Plain text</r3d:contentType>
                    <r3d:contentType contentTypeScheme="parse">Raw data</r3d:contentType>
                    <r3d:contentType contentTypeScheme="parse">Scientific and statistical data formats</r3d:contentType>
                    <r3d:contentType contentTypeScheme="parse">Standard office documents</r3d:contentType>
                    <r3d:contentType contentTypeScheme="parse">Structured text</r3d:contentType>
                            <r3d:providerType>dataProvider</r3d:providerType>
                            <r3d:keyword>bibliometrics</r3d:keyword>
                    <r3d:keyword>geolocation</r3d:keyword>
                    <r3d:keyword>information modeling</r3d:keyword>
                    <r3d:keyword>information science</r3d:keyword>
                    <r3d:keyword>large-scale data</r3d:keyword>
                    <r3d:keyword>multidisciplinary</r3d:keyword>
                            <r3d:institution>
                <r3d:institutionName language="eng">Indiana University, Cyberinfrastructure for Network Science Center</r3d:institutionName>
                                    <r3d:institutionAdditionalName language="eng">CNS</r3d:institutionAdditionalName>
                                <r3d:institutionCountry>USA</r3d:institutionCountry>
                                    <r3d:responsibilityType>general</r3d:responsibilityType>
                                <r3d:institutionType>non-profit</r3d:institutionType>
                <r3d:institutionURL>https://cns.iu.edu//</r3d:institutionURL>
                                <r3d:responsibilityStartDate></r3d:responsibilityStartDate>
                <r3d:responsibilityEndDate></r3d:responsibilityEndDate>
                                    <r3d:institutionContact>sjhale@indiana.edu</r3d:institutionContact>
                            </r3d:institution>
                    <r3d:institution>
                <r3d:institutionName language="eng">Indiana University, School of Informatics, Computing, and Engineering</r3d:institutionName>
                                    <r3d:institutionAdditionalName language="eng">formerly: Indiana University, School of Library and Information Science</r3d:institutionAdditionalName>
                                <r3d:institutionCountry>USA</r3d:institutionCountry>
                                    <r3d:responsibilityType>funding</r3d:responsibilityType>
                                <r3d:institutionType>non-profit</r3d:institutionType>
                <r3d:institutionURL>https://ils.indiana.edu/</r3d:institutionURL>
                                <r3d:responsibilityStartDate></r3d:responsibilityStartDate>
                <r3d:responsibilityEndDate></r3d:responsibilityEndDate>
                                    <r3d:institutionContact>https://ils.indiana.edu/contact/</r3d:institutionContact>
                            </r3d:institution>
                    <r3d:institution>
                <r3d:institutionName language="eng">James S. McDonnell Foundation</r3d:institutionName>
                                    <r3d:institutionAdditionalName language="eng">JSMF</r3d:institutionAdditionalName>
                                <r3d:institutionCountry>USA</r3d:institutionCountry>
                                    <r3d:responsibilityType>funding</r3d:responsibilityType>
                                <r3d:institutionType>non-profit</r3d:institutionType>
                <r3d:institutionURL>https://www.jsmf.org/</r3d:institutionURL>
                                    <r3d:institutionIdentifier>ROR:03dy4aq19</r3d:institutionIdentifier>
                                    <r3d:institutionIdentifier>RRID:SCR_006341</r3d:institutionIdentifier>
                                    <r3d:institutionIdentifier>RRID:nlx_152052</r3d:institutionIdentifier>
                                <r3d:responsibilityStartDate></r3d:responsibilityStartDate>
                <r3d:responsibilityEndDate></r3d:responsibilityEndDate>
                                    <r3d:institutionContact>info@jsmf.org</r3d:institutionContact>
                            </r3d:institution>
                    <r3d:institution>
                <r3d:institutionName language="eng">National Science Foundation</r3d:institutionName>
                                    <r3d:institutionAdditionalName language="eng">NSF</r3d:institutionAdditionalName>
                                <r3d:institutionCountry>USA</r3d:institutionCountry>
                                    <r3d:responsibilityType>funding</r3d:responsibilityType>
                                <r3d:institutionType>non-profit</r3d:institutionType>
                <r3d:institutionURL>https://www.nsf.gov/</r3d:institutionURL>
                                    <r3d:institutionIdentifier>ROR:021nxhr62</r3d:institutionIdentifier>
                                    <r3d:institutionIdentifier>RRID:SCR_012938</r3d:institutionIdentifier>
                                    <r3d:institutionIdentifier>RRID:nlx_inv_1005118</r3d:institutionIdentifier>
                                <r3d:responsibilityStartDate></r3d:responsibilityStartDate>
                <r3d:responsibilityEndDate></r3d:responsibilityEndDate>
                                    <r3d:institutionContact>info@nsf.gov</r3d:institutionContact>
                            </r3d:institution>
                            <r3d:policy>
                <r3d:policyName>Intellectual Property Policy</r3d:policyName>
                <r3d:policyURL>https://policies.iu.edu/policies/ua-05-intellectual-property/index.html</r3d:policyURL>
            </r3d:policy>
                    <r3d:policy>
                <r3d:policyName>University Policies</r3d:policyName>
                <r3d:policyURL>https://policies.iu.edu/index.html</r3d:policyURL>
            </r3d:policy>
                <r3d:databaseAccess>
            <r3d:databaseAccessType>restricted</r3d:databaseAccessType>
                            <r3d:databaseAccessRestriction>registration</r3d:databaseAccessRestriction>
                    </r3d:databaseAccess>
                            <r3d:dataAccess>
                <r3d:dataAccessType>restricted</r3d:dataAccessType>
                                    <r3d:dataAccessRestriction>other</r3d:dataAccessRestriction>
                            </r3d:dataAccess>
                    <r3d:dataAccess>
                <r3d:dataAccessType>restricted</r3d:dataAccessType>
                                    <r3d:dataAccessRestriction>registration</r3d:dataAccessRestriction>
                            </r3d:dataAccess>
                            <r3d:dataLicense>
                <r3d:dataLicenseName>Copyrights</r3d:dataLicenseName>
                <r3d:dataLicenseURL>https://www.iu.edu/copyright/index.html</r3d:dataLicenseURL>
            </r3d:dataLicense>
                            <r3d:dataUpload>
                <r3d:dataUploadType>closed</r3d:dataUploadType>
                            </r3d:dataUpload>
                                    <r3d:software>
                <r3d:softwareName>other</r3d:softwareName>
            </r3d:software>
                <r3d:versioning>yes</r3d:versioning>
                            <r3d:pidSystem>none</r3d:pidSystem>
                <r3d:citationGuidelineURL></r3d:citationGuidelineURL>
                <r3d:enhancedPublication>unknown</r3d:enhancedPublication>
        <r3d:qualityManagement>unknown</r3d:qualityManagement>
                                <r3d:remarks></r3d:remarks>
        <r3d:entryDate>2014-08-13</r3d:entryDate>
        <r3d:lastUpdate>2021-12-23</r3d:lastUpdate>
    </r3d:repository>
</r3d:re3data>