<?xml version="1.0" encoding="utf-8"?>
<!--re3data.org Schema for the Description of Research Data Repositories. Version 2.2, December 2014. doi:10.2312/re3.006-->
<r3d:re3data xmlns:r3d="http://www.re3data.org/schema/2-2" xmlns:xsi="http://www.w3.org/2001/XMLSchema-instance" xsi:schemaLocation="http://www.re3data.org/schema/2-2 http://schema.re3data.org/2-2/re3dataV2-2.xsd">
    <r3d:repository>
        <r3d:re3data.orgIdentifier>r3d100011147</r3d:re3data.orgIdentifier>
        <r3d:repositoryName language="eng">Forest Service Research Data Archive</r3d:repositoryName>
                    <r3d:additionalName language="eng">FSRDA</r3d:additionalName>
                <r3d:repositoryURL>https://www.fs.usda.gov/rds/archive/</r3d:repositoryURL>
                    <r3d:repositoryIdentifier>FAIRsharing_doi:10.25504/FAIRsharing.NzKTvN</r3d:repositoryIdentifier>
                <r3d:description language="eng">The Forest Service Research Data Archive is an actively curated repository for the long-term preservation and distribution of citable research data sets that are broadly relevant to forest and grassland ecology, and the economic and social interactions of humans with these ecosystems. Most data sets were created by U.S. Forest Service scientists or by scientists funded through the U.S. Forest Service or the U.S. Joint Fire Science Program.</r3d:description>
                    <r3d:repositoryContact>dave.rugg@usda.gov</r3d:repositoryContact>
                    <r3d:repositoryContact>https://www.fs.usda.gov/rds/archive/contactus</r3d:repositoryContact>
                    <r3d:repositoryContact>laurie.s.porth@usda.gov</r3d:repositoryContact>
                            <r3d:type>disciplinary</r3d:type>
                <r3d:size updated=""></r3d:size>
        <r3d:startDate></r3d:startDate>
        <r3d:endDate></r3d:endDate>
                    <r3d:repositoryLanguage>eng</r3d:repositoryLanguage>
                            <r3d:subject subjectScheme="DFG">2 Life Sciences</r3d:subject>
                    <r3d:subject subjectScheme="DFG">207 Agriculture, Forestry, Horticulture and Veterinary Medicine</r3d:subject>
                    <r3d:subject subjectScheme="DFG">20710 Basic Forest Research</r3d:subject>
                    <r3d:subject subjectScheme="DFG">21 Biology</r3d:subject>
                    <r3d:subject subjectScheme="DFG">23 Agriculture, Forestry, Horticulture and Veterinary Medicine</r3d:subject>
                <r3d:missionStatementURL>https://www.fs.usda.gov/rds/archive/</r3d:missionStatementURL>
                    <r3d:contentType contentTypeScheme="parse">Audiovisual data</r3d:contentType>
                    <r3d:contentType contentTypeScheme="parse">Databases</r3d:contentType>
                    <r3d:contentType contentTypeScheme="parse">Images</r3d:contentType>
                    <r3d:contentType contentTypeScheme="parse">Plain text</r3d:contentType>
                    <r3d:contentType contentTypeScheme="parse">Scientific and statistical data formats</r3d:contentType>
                    <r3d:contentType contentTypeScheme="parse">Structured text</r3d:contentType>
                            <r3d:providerType>dataProvider</r3d:providerType>
                            <r3d:keyword>ecosystem</r3d:keyword>
                    <r3d:keyword>forestry</r3d:keyword>
                    <r3d:keyword>sustainability</r3d:keyword>
                            <r3d:institution>
                <r3d:institutionName language="eng">United States Department of Agriculture, Forest Service</r3d:institutionName>
                                    <r3d:institutionAdditionalName language="eng">USDA</r3d:institutionAdditionalName>
                                <r3d:institutionCountry>USA</r3d:institutionCountry>
                                    <r3d:responsibilityType>funding</r3d:responsibilityType>
                                    <r3d:responsibilityType>general</r3d:responsibilityType>
                                <r3d:institutionType>non-profit</r3d:institutionType>
                <r3d:institutionURL>https://www.fs.usda.gov/</r3d:institutionURL>
                                    <r3d:institutionIdentifier>ROR:03zmjc935</r3d:institutionIdentifier>
                                <r3d:responsibilityStartDate></r3d:responsibilityStartDate>
                <r3d:responsibilityEndDate></r3d:responsibilityEndDate>
                                    <r3d:institutionContact>https://www.fs.usda.gov/rds/archive/contactus</r3d:institutionContact>
                            </r3d:institution>
                        <r3d:databaseAccess>
            <r3d:databaseAccessType>open</r3d:databaseAccessType>
                    </r3d:databaseAccess>
                            <r3d:dataAccess>
                <r3d:dataAccessType>open</r3d:dataAccessType>
                            </r3d:dataAccess>
                            <r3d:dataLicense>
                <r3d:dataLicenseName>other</r3d:dataLicenseName>
                <r3d:dataLicenseURL>https://www.fs.usda.gov/rds/archive/DataUseInfo</r3d:dataLicenseURL>
            </r3d:dataLicense>
                            <r3d:dataUpload>
                <r3d:dataUploadType>restricted</r3d:dataUploadType>
                                    <r3d:dataUploadRestriction>other</r3d:dataUploadRestriction>
                            </r3d:dataUpload>
                                    <r3d:software>
                <r3d:softwareName>unknown</r3d:softwareName>
            </r3d:software>
                <r3d:versioning></r3d:versioning>
                            <r3d:pidSystem>DOI</r3d:pidSystem>
                <r3d:citationGuidelineURL>https://www.fs.usda.gov/rds/archive/DataUseInfo</r3d:citationGuidelineURL>
                <r3d:enhancedPublication>no</r3d:enhancedPublication>
        <r3d:qualityManagement>yes</r3d:qualityManagement>
                            <r3d:metadataStandard>
                <r3d:metadataStandardName metadataStandardScheme="DCC">FGDC/CSDGM - Federal Geographic Data Committee Content Standard for Digital Geospatial Metadata</r3d:metadataStandardName>
                <r3d:metadataStandardURL>http://www.dcc.ac.uk/resources/metadata-standards/fgdccsdgm-federal-geographic-data-committee-content-standard-digital-ge</r3d:metadataStandardURL>
            </r3d:metadataStandard>
                    <r3d:metadataStandard>
                <r3d:metadataStandardName metadataStandardScheme="DCC">ISO 19115</r3d:metadataStandardName>
                <r3d:metadataStandardURL>http://www.dcc.ac.uk/resources/metadata-standards/iso-19115</r3d:metadataStandardURL>
            </r3d:metadataStandard>
                        <r3d:remarks>Forest Service Research Data Archive is covered by Thomson Reuters Data Citation Index.</r3d:remarks>
        <r3d:entryDate>2014-10-08</r3d:entryDate>
        <r3d:lastUpdate>2022-03-24</r3d:lastUpdate>
    </r3d:repository>
</r3d:re3data>